dummy/__init__.py
dummy/add.py
dummy/calc.py
dummy/mul.py
dummy/sub.py
py_dummy-0.1.0.data/data/icons/Dummy.ico
py_dummy-0.1.0.data/data/icons/Dummy.png
py_dummy-0.1.0.data/scripts/dummy
py_dummy-0.1.0.dist-info/DESCRIPTION.rst
py_dummy-0.1.0.dist-info/METADATA
py_dummy-0.1.0.dist-info/RECORD
py_dummy-0.1.0.dist-info/WHEEL
py_dummy-0.1.0.dist-info/metadata.json
py_dummy-0.1.0.dist-info/top_level.txt
